s365dispatcher/DispatcherClient.py
s365dispatcher/__init__.py
s365dispatcher/models/ActionModel.py
s365dispatcher/models/EmailActionModel.py
s365dispatcher/models/Environment.py
s365dispatcher/models/ExternalClientResultResponseModel.py
s365dispatcher/models/FormParameterModel.py
s365dispatcher/models/HeaderModel.py
s365dispatcher/models/InputParameterModel.py
s365dispatcher/models/JobActionTriggerOn.py
s365dispatcher/models/JobActionType.py
s365dispatcher/models/JobProcessingStatus.py
s365dispatcher/models/JobType.py
s365dispatcher/models/NewJobFromFilterPostModel.py
s365dispatcher/models/NewJobPostModel.py
s365dispatcher/models/OutputParameterModel.py
s365dispatcher/models/SettingsModel.py
s365dispatcher/models/WebHookActionHttpMethod.py
s365dispatcher/models/WebHookActionModel.py
s365dispatcher/models/WebHookActionPayloadType.py
s365dispatcher/models/__init__.py
simulate365py/__init__.py
simulate365py/dispatcher/DispatcherClient.py
simulate365py/dispatcher/__init__.py
simulate365py/dispatcher/models/ActionModel.py
simulate365py/dispatcher/models/EmailActionModel.py
simulate365py/dispatcher/models/Environment.py
simulate365py/dispatcher/models/ExternalClientResultResponseModel.py
simulate365py/dispatcher/models/FormParameterModel.py
simulate365py/dispatcher/models/HeaderModel.py
simulate365py/dispatcher/models/InputParameterModel.py
simulate365py/dispatcher/models/JobActionTriggerOn.py
simulate365py/dispatcher/models/JobActionType.py
simulate365py/dispatcher/models/JobProcessingStatus.py
simulate365py/dispatcher/models/JobType.py
simulate365py/dispatcher/models/NewJobFromFilterPostModel.py
simulate365py/dispatcher/models/NewJobPostModel.py
simulate365py/dispatcher/models/OutputParameterModel.py
simulate365py/dispatcher/models/SettingsModel.py
simulate365py/dispatcher/models/WebHookActionHttpMethod.py
simulate365py/dispatcher/models/WebHookActionModel.py
simulate365py/dispatcher/models/WebHookActionPayloadType.py
simulate365py/dispatcher/models/__init__.py
simulate365py-1.0.0.dist-info/METADATA
simulate365py-1.0.0.dist-info/WHEEL
simulate365py-1.0.0.dist-info/top_level.txt
simulate365py-1.0.0.dist-info/RECORD
