Metadata-Version: 2.1
Name: simulate365py
Version: 1.0.0
Summary: Client for Simulate 365 Dispatcher
Home-page: UNKNOWN
Author: CGC Capital-Gain Consultants GmbH
License: CGC EULA
Platform: UNKNOWN
